{
  "planning_data": {
    "total_files": 0,
    "gtfs_files": 0,
    "netex_files": 0,
    "edifact_files": 0,
    "rawdata_files": 0
  },
  "realtime_data": {
    "with_platform_changes": 0,
    "without_platform_changes": 0
  },
  "metadata": {
    "generated_at": "2025-12-08T19:28:10.914678",
    "planning_dir": "C:\\Users\\sande\\Documents\\GitHub\\NMBS-Train-data\\reports",
    "realtime_dir": "C:\\Users\\sande\\Documents\\GitHub\\NMBS-Train-data\\reports\\realtime",
    "data_source": "API"
  },
  "realtime_stats": {
    "with_platform_changes_count": 0,
    "without_platform_changes_count": 0,
    "with_platform_changes_percent": 0,
    "without_platform_changes_percent": 0,
    "generated_at": "2025-12-08T19:28:10.914688"
  }
}